ciperror/__init__.py
ciperror/base_ciperror.py
ciperror/callback_errors.py
ciperror/configuration_error.py
ciperror/connection_errors.py
ciperror/database_errors.py
ciperror/elemental_errors.py
ciperror/encoding_factory_errors.py
ciperror/file_copy_service_errors.py
ciperror/ftp_general_errors.py
ciperror/general_api_errors.py
ciperror/general_expected_errors.py
ciperror/general_file_system_errors.py
ciperror/general_unexpected_errors.py
ciperror/general_view_errors.py
ciperror/index_errors.py
ciperror/input_output_errors.py
ciperror/job_data_service_errors.py
ciperror/ladder_service_errors.py
ciperror/transcoder_errors.py
ciperror-1.0.52.dist-info/METADATA
ciperror-1.0.52.dist-info/WHEEL
ciperror-1.0.52.dist-info/top_level.txt
ciperror-1.0.52.dist-info/RECORD
