Metadata-Version: 2.1
Name: ciperror
Version: 1.0.52
Summary: TCIP error definitions.
Home-page: UNKNOWN
Author: Gustavo Alves
Author-email: gustavo.oliveira@tvlgobo.com.br
License: MIT
Platform: UNKNOWN
